CHANGES.txt
MANIFEST.in
README.txt
setup.py
docs/Makefile
docs/conf.py
docs/index.rst
docs/make.bat
quantumcore/__init__.py
quantumcore.contenttypes.egg-info/PKG-INFO
quantumcore.contenttypes.egg-info/SOURCES.txt
quantumcore.contenttypes.egg-info/dependency_links.txt
quantumcore.contenttypes.egg-info/entry_points.txt
quantumcore.contenttypes.egg-info/namespace_packages.txt
quantumcore.contenttypes.egg-info/not-zip-safe
quantumcore.contenttypes.egg-info/requires.txt
quantumcore.contenttypes.egg-info/top_level.txt
quantumcore/contenttypes/__init__.py
quantumcore/contenttypes/__init__.pyc
quantumcore/contenttypes/globs.py
quantumcore/contenttypes/globs.pyc
quantumcore/contenttypes/magic.py
quantumcore/contenttypes/mimetype.py
quantumcore/contenttypes/registry.py
quantumcore/contenttypes/registry.pyc
quantumcore/contenttypes/data/sharedmime/XMLnamespaces
quantumcore/contenttypes/data/sharedmime/aliases
quantumcore/contenttypes/data/sharedmime/generic-icons
quantumcore/contenttypes/data/sharedmime/globs
quantumcore/contenttypes/data/sharedmime/globs2
quantumcore/contenttypes/data/sharedmime/icons
quantumcore/contenttypes/data/sharedmime/magic
quantumcore/contenttypes/data/sharedmime/subclasses
quantumcore/contenttypes/data/sharedmime/treemagic
quantumcore/contenttypes/data/sharedmime/types
quantumcore/contenttypes/data/sharedmime/all/all.xml
quantumcore/contenttypes/data/sharedmime/all/allfiles.xml
quantumcore/contenttypes/data/sharedmime/application/andrew-inset.xml
quantumcore/contenttypes/data/sharedmime/application/annodex.xml
quantumcore/contenttypes/data/sharedmime/application/atom+xml.xml
quantumcore/contenttypes/data/sharedmime/application/dicom.xml
quantumcore/contenttypes/data/sharedmime/application/docbook+xml.xml
quantumcore/contenttypes/data/sharedmime/application/ecmascript.xml
quantumcore/contenttypes/data/sharedmime/application/epub+zip.xml
quantumcore/contenttypes/data/sharedmime/application/gnunet-directory.xml
quantumcore/contenttypes/data/sharedmime/application/illustrator.xml
quantumcore/contenttypes/data/sharedmime/application/javascript.xml
quantumcore/contenttypes/data/sharedmime/application/mac-binhex40.xml
quantumcore/contenttypes/data/sharedmime/application/mathematica.xml
quantumcore/contenttypes/data/sharedmime/application/mathml+xml.xml
quantumcore/contenttypes/data/sharedmime/application/mbox.xml
