Metadata-Version: 1.0
Name: quantumcore.contenttypes
Version: 0.1.1
Summary: A content type detection library using the freedesktop shared mime database
Home-page: http://quantumcore.org/
Author: Christian Scholz
Author-email: cs@comlounge.net
License: GPL
Keywords: mimetypes mimetype contenttype magic detection types freedesktop sharedmime mime quantumcore
Platform: UNKNOWN
Classifier: Programming Language :: Python
